{
    "name": "root",
    "gauges": {
        "AirplaneAI.Policy.Entropy.mean": {
            "value": -2.784963369369507,
            "min": -2.784963369369507,
            "max": 1.4079371690750122,
            "count": 149
        },
        "AirplaneAI.Policy.Entropy.sum": {
            "value": -139203.609375,
            "min": -139203.609375,
            "max": 70978.3359375,
            "count": 149
        },
        "AirplaneAI.Step.mean": {
            "value": 7449977.0,
            "min": 49971.0,
            "max": 7449977.0,
            "count": 149
        },
        "AirplaneAI.Step.sum": {
            "value": 7449977.0,
            "min": 49971.0,
            "max": 7449977.0,
            "count": 149
        },
        "AirplaneAI.Policy.ExtrinsicValueEstimate.mean": {
            "value": -11.504714965820312,
            "min": -23.78121566772461,
            "max": -3.1103105545043945,
            "count": 149
        },
        "AirplaneAI.Policy.ExtrinsicValueEstimate.sum": {
            "value": -9123.2392578125,
            "min": -18929.84765625,
            "max": -2478.91748046875,
            "count": 149
        },
        "AirplaneAI.Policy.GailValueEstimate.mean": {
            "value": 18.180471420288086,
            "min": 3.0194742679595947,
            "max": 26.950029373168945,
            "count": 149
        },
        "AirplaneAI.Policy.GailValueEstimate.sum": {
            "value": 14417.11328125,
            "min": 2406.52099609375,
            "max": 21344.423828125,
            "count": 149
        },
        "AirplaneAI.Environment.EpisodeLength.mean": {
            "value": 2099.793103448276,
            "min": 1193.2727272727273,
            "max": 2468.0,
            "count": 149
        },
        "AirplaneAI.Environment.EpisodeLength.sum": {
            "value": 60894.0,
            "min": 39378.0,
            "max": 61693.0,
            "count": 149
        },
        "AirplaneAI.Environment.CumulativeReward.mean": {
            "value": -583.0075971340311,
            "min": -1153.2101231643132,
            "max": -99.19523770858844,
            "count": 149
        },
        "AirplaneAI.Environment.CumulativeReward.sum": {
            "value": -16907.220316886902,
            "min": -36051.305643603206,
            "max": -2380.6857050061226,
            "count": 149
        },
        "AirplaneAI.Policy.ExtrinsicReward.mean": {
            "value": -577.1775375255223,
            "min": -1141.6780396245774,
            "max": -98.2032975666225,
            "count": 149
        },
        "AirplaneAI.Policy.ExtrinsicReward.sum": {
            "value": -16738.148588240147,
            "min": -35690.7930777967,
            "max": -2356.87914159894,
            "count": 149
        },
        "AirplaneAI.Policy.GailReward.mean": {
            "value": 392.35083667368724,
            "min": 297.3043026285013,
            "max": 791.4353859421204,
            "count": 149
        },
        "AirplaneAI.Policy.GailReward.sum": {
            "value": 11378.17426353693,
            "min": 7571.931294679642,
            "max": 17786.21215498075,
            "count": 149
        },
        "AirplaneAI.Losses.PolicyLoss.mean": {
            "value": 0.02318947479487785,
            "min": 0.019155722129604934,
            "max": 0.028373467721667114,
            "count": 149
        },
        "AirplaneAI.Losses.PolicyLoss.sum": {
            "value": 0.11594737397438924,
            "min": 0.08308761834923643,
            "max": 0.13878532405360602,
            "count": 149
        },
        "AirplaneAI.Losses.ValueLoss.mean": {
            "value": 66.02994937260947,
            "min": 34.90097078641255,
            "max": 1650.1690690867108,
            "count": 149
        },
        "AirplaneAI.Losses.ValueLoss.sum": {
            "value": 330.1497468630473,
            "min": 162.03304117520653,
            "max": 8250.845345433554,
            "count": 149
        },
        "AirplaneAI.Policy.LearningRate.mean": {
            "value": 7.7363156212306e-05,
            "min": 7.7363156212306e-05,
            "max": 0.00029922828775723743,
            "count": 149
        },
        "AirplaneAI.Policy.LearningRate.sum": {
            "value": 0.00038681578106153,
            "min": 0.00031499645500127993,
            "max": 0.0014892062735979098,
            "count": 149
        },
        "AirplaneAI.Policy.Epsilon.mean": {
            "value": 0.12578769400000003,
            "min": 0.12578769400000003,
            "max": 0.19974276250000003,
            "count": 149
        },
        "AirplaneAI.Policy.Epsilon.sum": {
            "value": 0.6289384700000001,
            "min": 0.5049987200000002,
            "max": 0.9964020900000001,
            "count": 149
        },
        "AirplaneAI.Policy.Beta.mean": {
            "value": 0.0012968059306,
            "min": 0.0012968059306,
            "max": 0.004987163848750001,
            "count": 149
        },
        "AirplaneAI.Policy.Beta.sum": {
            "value": 0.006484029653,
            "min": 0.005279436128000001,
            "max": 0.024820464291000006,
            "count": 149
        },
        "AirplaneAI.Policy.GAILPolicyEstimate.mean": {
            "value": 0.2597785850365957,
            "min": 0.2354643599440654,
            "max": 0.35211466093858085,
            "count": 149
        },
        "AirplaneAI.Policy.GAILPolicyEstimate.sum": {
            "value": 1.2988929251829784,
            "min": 0.9418574397762616,
            "max": 1.7605733046929042,
            "count": 149
        },
        "AirplaneAI.Policy.GAILExpertEstimate.mean": {
            "value": 0.8452570315202077,
            "min": 0.7130864040056863,
            "max": 0.8452570315202077,
            "count": 149
        },
        "AirplaneAI.Policy.GAILExpertEstimate.sum": {
            "value": 4.226285157601039,
            "min": 2.926362003882726,
            "max": 4.226285157601039,
            "count": 149
        },
        "AirplaneAI.Losses.GAILLoss.mean": {
            "value": 0.49796116769313814,
            "min": 0.4968323181072871,
            "max": 1.23710929180185,
            "count": 149
        },
        "AirplaneAI.Losses.GAILLoss.sum": {
            "value": 2.4898058384656907,
            "min": 1.9873292724291485,
            "max": 4.9484371672074,
            "count": 149
        },
        "AirplaneAI.Policy.GAILGradMagLoss.mean": {
            "value": 0.15025622328122457,
            "min": 0.15025622328122457,
            "max": 9.297879481315613,
            "count": 149
        },
        "AirplaneAI.Policy.GAILGradMagLoss.sum": {
            "value": 0.7512811164061228,
            "min": 0.6074455946683883,
            "max": 37.19151792526245,
            "count": 149
        },
        "AirplaneAI.Losses.PretrainingLoss.mean": {
            "value": 0.004459376621525735,
            "min": 0.004459376621525735,
            "max": 1.0565942058960596,
            "count": 149
        },
        "AirplaneAI.Losses.PretrainingLoss.sum": {
            "value": 0.022296883107628673,
            "min": 0.018163940298836678,
            "max": 4.925169150034587,
            "count": 149
        },
        "AirplaneAI.IsTraining.mean": {
            "value": 1.0,
            "min": 1.0,
            "max": 1.0,
            "count": 149
        },
        "AirplaneAI.IsTraining.sum": {
            "value": 1.0,
            "min": 1.0,
            "max": 1.0,
            "count": 149
        }
    },
    "metadata": {
        "timer_format_version": "0.1.0",
        "start_time_seconds": "1674809844",
        "python_version": "3.8.15 (default, Nov 24 2022, 14:38:14) [MSC v.1916 64 bit (AMD64)]",
        "command_line_arguments": "C:\\Users\\jarne\\miniconda3\\envs\\mlagents\\Scripts\\mlagents-learn Assets/AirplaneAI/Config/learnToFly.yaml --quality-level=0 --run-id=NoObstacleImitation2 --force",
        "mlagents_version": "0.30.0",
        "mlagents_envs_version": "0.30.0",
        "communication_protocol_version": "1.5.0",
        "pytorch_version": "1.13.1",
        "numpy_version": "1.23.5",
        "end_time_seconds": "1674823545"
    },
    "total": 13701.6302419,
    "count": 1,
    "self": 0.017891500001496752,
    "children": {
        "run_training.setup": {
            "total": 0.06617359999999994,
            "count": 1,
            "self": 0.06617359999999994
        },
        "TrainerController.start_learning": {
            "total": 13701.546176799999,
            "count": 1,
            "self": 15.14239150028152,
            "children": {
                "TrainerController._reset_env": {
                    "total": 25.6146347,
                    "count": 1,
                    "self": 15.990498599999999,
                    "children": {
                        "demo_to_buffer": {
                            "total": 9.624136100000001,
                            "count": 2,
                            "self": 0.0003302000000005023,
                            "children": {
                                "load_demonstration": {
                                    "total": 0.28533760000000186,
                                    "count": 2,
                                    "self": 0.2771975000000033,
                                    "children": {
                                        "read_file": {
                                            "total": 0.00814009999999854,
                                            "count": 2,
                                            "self": 0.00814009999999854
                                        }
                                    }
                                },
                                "make_demo_buffer": {
                                    "total": 9.338468299999999,
                                    "count": 2,
                                    "self": 1.5469177999998784,
                                    "children": {
                                        "steps_from_proto": {
                                            "total": 7.79155050000012,
                                            "count": 82696,
                                            "self": 4.808643100000207,
                                            "children": {
                                                "_process_rank_one_or_two_observation": {
                                                    "total": 2.982907399999913,
                                                    "count": 330784,
                                                    "self": 2.982907399999913
                                                }
                                            }
                                        }
                                    }
                                }
                            }
                        }
                    }
                },
                "TrainerController.advance": {
                    "total": 13660.463489799718,
                    "count": 679267,
                    "self": 7.114579499435422,
                    "children": {
                        "env_step": {
                            "total": 13653.348910300283,
                            "count": 679267,
                            "self": 6851.289408899976,
                            "children": {
                                "SubprocessEnvManager._take_step": {
                                    "total": 6794.467416800163,
                                    "count": 679268,
                                    "self": 38.15153270033352,
                                    "children": {
                                        "TorchPolicy.evaluate": {
                                            "total": 6756.315884099829,
                                            "count": 679268,
                                            "self": 6756.315884099829
                                        }
                                    }
                                },
                                "workers": {
                                    "total": 7.592084600144954,
                                    "count": 679266,
                                    "self": 0.0,
                                    "children": {
                                        "worker_root": {
                                            "total": 13595.175491600445,
                                            "count": 679266,
                                            "is_parallel": true,
                                            "self": 9117.860614200748,
                                            "children": {
                                                "steps_from_proto": {
                                                    "total": 0.0014605000000056378,
                                                    "count": 2,
                                                    "is_parallel": true,
                                                    "self": 0.0006577000000014266,
                                                    "children": {
                                                        "_process_rank_one_or_two_observation": {
                                                            "total": 0.0008028000000042113,
                                                            "count": 8,
                                                            "is_parallel": true,
                                                            "self": 0.0008028000000042113
                                                        }
                                                    }
                                                },
                                                "UnityEnvironment.step": {
                                                    "total": 4477.313416899697,
                                                    "count": 679266,
                                                    "is_parallel": true,
                                                    "self": 101.50481609935923,
                                                    "children": {
                                                        "UnityEnvironment._generate_step_input": {
                                                            "total": 154.72857539944195,
                                                            "count": 679266,
                                                            "is_parallel": true,
                                                            "self": 154.72857539944195
                                                        },
                                                        "communicator.exchange": {
                                                            "total": 3937.502633100872,
                                                            "count": 679266,
                                                            "is_parallel": true,
                                                            "self": 3937.502633100872
                                                        },
                                                        "steps_from_proto": {
                                                            "total": 283.57739230002363,
                                                            "count": 679266,
                                                            "is_parallel": true,
                                                            "self": 114.18901209976787,
                                                            "children": {
                                                                "_process_rank_one_or_two_observation": {
                                                                    "total": 169.38838020025577,
                                                                    "count": 2717064,
                                                                    "is_parallel": true,
                                                                    "self": 169.38838020025577
                                                                }
                                                            }
                                                        }
                                                    }
                                                }
                                            }
                                        }
                                    }
                                }
                            }
                        }
                    }
                },
                "trainer_threads": {
                    "total": 8.469999920635018e-05,
                    "count": 1,
                    "self": 8.469999920635018e-05,
                    "children": {
                        "thread_root": {
                            "total": 0.0,
                            "count": 0,
                            "is_parallel": true,
                            "self": 0.0,
                            "children": {
                                "trainer_advance": {
                                    "total": 13667.3803740003,
                                    "count": 618696,
                                    "is_parallel": true,
                                    "self": 28.11336990010932,
                                    "children": {
                                        "process_trajectory": {
                                            "total": 9282.013027100193,
                                            "count": 618696,
                                            "is_parallel": true,
                                            "self": 9280.041459600194,
                                            "children": {
                                                "RLTrainer._checkpoint": {
                                                    "total": 1.9715674999997646,
                                                    "count": 14,
                                                    "is_parallel": true,
                                                    "self": 1.9715674999997646
                                                }
                                            }
                                        },
                                        "_update_policy": {
                                            "total": 4357.253976999998,
                                            "count": 726,
                                            "is_parallel": true,
                                            "self": 3211.8838011998414,
                                            "children": {
                                                "TorchPPOOptimizer.update": {
                                                    "total": 1145.370175800156,
                                                    "count": 21780,
                                                    "is_parallel": true,
                                                    "self": 1145.370175800156
                                                }
                                            }
                                        }
                                    }
                                }
                            }
                        }
                    }
                },
                "TrainerController._save_models": {
                    "total": 0.3255761000000348,
                    "count": 1,
                    "self": 0.011706100000083097,
                    "children": {
                        "RLTrainer._checkpoint": {
                            "total": 0.3138699999999517,
                            "count": 1,
                            "self": 0.3138699999999517
                        }
                    }
                }
            }
        }
    }
}